<mediawiki xmlns="http://www.mediawiki.org/xml/export-0.10/" xmlns:xsi="http://www.w3.org/2001/XMLSchema-instance" xsi:schemaLocation="http://www.mediawiki.org/xml/export-0.10/ http://www.mediawiki.org/xml/export-0.10.xsd" version="0.10" xml:lang="en">
  <siteinfo>
    <sitename>Wikipedia</sitename>
    <dbname>enwiki</dbname>
    <base>https://en.wikipedia.org/wiki/Main_Page</base>
    <generator>MediaWiki 1.35.0-wmf.36</generator>
    <case>first-letter</case>
    <namespaces>
      <namespace key="-2" case="first-letter">Media</namespace>
      <namespace key="-1" case="first-letter">Special</namespace>
      <namespace key="0" case="first-letter" />
      <namespace key="1" case="first-letter">Talk</namespace>
      <namespace key="2" case="first-letter">User</namespace>
      <namespace key="3" case="first-letter">User talk</namespace>
      <namespace key="4" case="first-letter">Wikipedia</namespace>
      <namespace key="5" case="first-letter">Wikipedia talk</namespace>
      <namespace key="6" case="first-letter">File</namespace>
      <namespace key="7" case="first-letter">File talk</namespace>
      <namespace key="8" case="first-letter">MediaWiki</namespace>
      <namespace key="9" case="first-letter">MediaWiki talk</namespace>
      <namespace key="10" case="first-letter">Template</namespace>
      <namespace key="11" case="first-letter">Template talk</namespace>
      <namespace key="12" case="first-letter">Help</namespace>
      <namespace key="13" case="first-letter">Help talk</namespace>
      <namespace key="14" case="first-letter">Category</namespace>
      <namespace key="15" case="first-letter">Category talk</namespace>
      <namespace key="100" case="first-letter">Portal</namespace>
      <namespace key="101" case="first-letter">Portal talk</namespace>
      <namespace key="108" case="first-letter">Book</namespace>
      <namespace key="109" case="first-letter">Book talk</namespace>
      <namespace key="118" case="first-letter">Draft</namespace>
      <namespace key="119" case="first-letter">Draft talk</namespace>
      <namespace key="446" case="first-letter">Education Program</namespace>
      <namespace key="447" case="first-letter">Education Program talk</namespace>
      <namespace key="710" case="first-letter">TimedText</namespace>
      <namespace key="711" case="first-letter">TimedText talk</namespace>
      <namespace key="828" case="first-letter">Module</namespace>
      <namespace key="829" case="first-letter">Module talk</namespace>
      <namespace key="2300" case="first-letter">Gadget</namespace>
      <namespace key="2301" case="first-letter">Gadget talk</namespace>
      <namespace key="2302" case="case-sensitive">Gadget definition</namespace>
      <namespace key="2303" case="case-sensitive">Gadget definition talk</namespace>
    </namespaces>
  </siteinfo>
  <page>
    <title>Hekat</title>
    <ns>0</ns>
    <id>9098286</id>
    <revision>
      <id>950270700</id>
      <parentid>950270663</parentid>
      <timestamp>2020-04-11T04:39:16Z</timestamp>
      <contributor>
        <username>Anthony Appleyard</username>
        <id>119438</id>
      </contributor>
      <comment>/* top */ ed</comment>
      <model>wikitext</model>
      <format>text/x-wiki</format>
      <text bytes="6377" xml:space="preserve">{{distinguish|Hecat}}
{{No footnotes|date=August 2017}}

The '''hekat''' or '''heqat''' (transcribed ''HqA.t'') was an [[ancient Egyptian weights and measures|ancient Egyptian volume unit]] used to measure grain, bread, and beer. 
It equals 4.8&amp;nbsp;[[litre]]s, or about 1.056 [[imperial gallon]]s, in today's measurements.&lt;ref name="alert"&gt;{{cite web|url=http://www.eurekalert.org/pub_releases/2012-06/afot-ajh060412.php|title=Ancient jugs hold the secret to practical mathematics in Biblical times|website=EurekAlert!}} retrieved March 22, 2020 at about 7:00 AM EST.&lt;/ref&gt;

==Overview==
Until the New Kingdom (NK), the hekat was one tenth of a khar, later one sixteenth; while the New Kingdom ''oipe'' (transcribed ''ip.t'') contained 4&amp;nbsp;hekat. It was sub-divided into other units &amp;ndash; some for  medical prescriptions &amp;ndash; the   ''hin'' (1/10), ''dja'' (1/64) and ''ro'' (1/320). The ''dja'' was recently evaluated by Tanja Pommerening in 2002 to 1/64 of a hekat (75 cc) in the MK, and 1/64 of an oipe (1/16 of a hekat, or 300 cc) in the NK, meaning that the ''dja'' was denoted by Horus-Eye imagery. It has been suggested by Pommerening that the NK change came about related to the oipe replacing the hekat as the Pharaonic volume control unit in official lists.

Hana Vymazalova evaluated the hekat unit in 2002 within the [[Akhmim Wooden Tablet]] by showing that five answers were returned to (64/64) when multiplied by the divisors 3, 7, 10, 11 and 13. The [[Rhind Mathematical Papyrus|RMP]] also divided a hekat unity (64/64) by prime and composite numbers ''n'' when 1/64&amp;nbsp;&lt;&amp;nbsp;''n''&amp;nbsp;&lt;&amp;nbsp;64. The binary quotient used [[Eye of Horus#In arithmetic|Eye of Horus]] numbers. The remainder scaled [[Egyptian fraction]]s to 1/320 units named ro. Quotients and unscaled remainders were obtained for the dja, ro and other units when the divisor ''n'' was greater than 64. For example, one the 1/320&amp;nbsp;ro unit was written by Ahmes by solving 320/n&amp;nbsp;ro. Gillings cites 29 examples of two-part statements converted to one-part statements in RMP 82. Ahmes recorded the ''n''&amp;nbsp;=&amp;nbsp;3 case by showing (64/64)/3&amp;nbsp;=&amp;nbsp;21/64&amp;nbsp;+&amp;nbsp;1/192 (a modern statement) as written as(16&amp;nbsp;+&amp;nbsp;4&amp;nbsp;+&amp;nbsp;1)/64&amp;nbsp;+&amp;nbsp;5/3&amp;nbsp;&amp;times;&amp;nbsp;1/320 =&amp;nbsp;1/4&amp;nbsp;+&amp;nbsp;1/16&amp;nbsp;+&amp;nbsp;1/64&amp;nbsp;+&amp;nbsp;1&amp;nbsp;2/3ro (two-part ancient statement). Two-part statements were also converted by Ahmes to an unscaled hin unit by writing&amp;nbsp;3&amp;nbsp;1/3&amp;nbsp;hin.

The hekat measurement unit, and its [[double entry accounting system]], was found beyond the [[Rhind Mathematical Papyrus]]. Another text was the [[Ebers Papyrus]], the best known medical text. The hekat unit was defined, in terms of its volume size, in the [[Moscow Mathematical Papyrus]] by MMP #10, by approximating ''[[&amp;pi;]]'' to around 3.16. The approximation of ''&amp;pi;'' was achieved by squaring a circle, increasingly (i.e. for the denominator in terms of setats: 9, 18, 36, 72, and 81, Gillings, page 141) until the vulgar fraction 256/81 was reached, the only relationship that was used in the Egyptian Middle Kingdom. The MMP scribe found the surface area of a basket equal to: (8d/9)&lt;sup&gt;2&lt;/sup&gt; =&amp;nbsp;64d&lt;sup&gt;2&lt;/sup&gt;/81, within a cylinder relationship to the hekat. MMP 10 data meant that ''d''&amp;nbsp;=&amp;nbsp;2 defined ''&amp;pi;'' for use in hekat volumes as&amp;nbsp;256/81. The 256/81 approximation was also used by [[Ahmes]] and other scribes. The [[ancient Egyptian weights and measures]] discussion further shows that the hekat was 1/30 of a royal cubit&lt;sup&gt;3&lt;/sup&gt;, an analysis that needs to double checked, against the ''d''&amp;nbsp;=&amp;nbsp;2 suggestion, which means that ''r''&amp;nbsp;=&amp;nbsp;1, a suggestion that does make sense. One royal cubit of the [[Ancient Egyptian weights and measures]] =&amp;nbsp;523.5&amp;nbsp;millimeters. ((523.5&amp;nbsp;mm)&lt;sup&gt;3&lt;/sup&gt;)&amp;nbsp;/&amp;nbsp;30 =&amp;nbsp;4.78221176&amp;nbsp;liters.

However that may be at least a sphere that has a circumference 523.5 millimeters will actually have a metric volume about 2.42269 liters or roughly half of a hekat or about one sixtieth of a royal cubic cubit to two parts in a hundred.  A modern schoolbook formula has volume=4/3 pi r&lt;sup&gt;3&lt;/sup&gt; for example.  In the case of a land where pi=256/81 or about 3.1604938 a similar result can be obtained with the different formula that has been suggested by Zapassky and others where over there the volume of a sphere is given by the quotient of the cube of the circumference divided by six pi&lt;sup&gt;2&lt;/sup&gt; (V=c&lt;sup&gt;3&lt;/sup&gt;/6π&lt;sup&gt;2&lt;/sup&gt;)&lt;ref&gt;Zapassky E, Gadot Y, Finkelstein I, Benenson I (2012) An Ancient Relation between Units of Length and Volume Based on a Sphere. PLoS ONE 7(3): e33895. https://journals.plos.org/plosone/article?id=10.1371/journal.pone.0033895 retrieved March 22, 2020 at about 7:38 AM EST&lt;/ref&gt; and in that case the ancient Egyptian volume should come to about 2.386954 liters or about 98.5% of its true volume.  
  
{{Reflist}}

==External links==
* http://www.eurekalert.org/pub_releases/2012-06/afot-ajh060412.php
* Gillings, Richard. ''Mathematics in the Time of the Pharaohs'' Dover, reprint from Cambridge, Mass, MIT Press 1972, {{ISBN|0-486-24315-X}}.
* Pommerening, Tanja, "Altagyptische Holmasse Metrologish neu Interpretiert" and relevant pharmaceutical and medical knowledge, an abstract,  Philipps-Universität, Marburg, 8-11-2004, taken from "Die Altagyptschen Hohlmass" in studien zur Altagyptischen Kulture, Beiheft, 10, Hamburg, Buske-Verlag, 2005
* Vymazalova, H. "The Wooden Tablets from Cairo: The Use of the Grain Unit HK3T in Ancient Egypt." ''Archiv Orientalai'', Charles U., Prague, pp.&amp;nbsp;27&amp;ndash;42, 2002.
* [http://www.eurekalert.org/pub_releases/2012-06/afot-ajh060412.php eurekalert.org]
* [http://planetmath.org/encyclopedia/HekatDivisionsEgyptianWeightsAndMeasures.html Hekat units in the RMP]
* [http://www.math.buffalo.edu/mad/Ancient-Africa/mad_ancient_egypt_geometry.html Egyptian geometry: Determining the value of ''&amp;pi;'']
* Benenson, Itzahk.  Some short paper in Hebrew about the noted 2012 pottery volumes studies that looks like it could not possibly have much particulars in it at https://tauweb.tau.ac.il/news/new-method-discovery-ancient-world retrieved March 21, 2020 at about 11:20 PM EST  

[[Category:History of mathematics]]
[[Category:Obsolete units of measurement]]
[[Category:Units of volume]]</text>
      <sha1>53uajnwwn4pzeqfds1s57ye5axc5pyn</sha1>
    </revision>
  </page>
</mediawiki>
