<mediawiki xmlns="http://www.mediawiki.org/xml/export-0.10/" xmlns:xsi="http://www.w3.org/2001/XMLSchema-instance" xsi:schemaLocation="http://www.mediawiki.org/xml/export-0.10/ http://www.mediawiki.org/xml/export-0.10.xsd" version="0.10" xml:lang="en">
  <siteinfo>
    <sitename>Wikipedia</sitename>
    <dbname>enwiki</dbname>
    <base>https://en.wikipedia.org/wiki/Main_Page</base>
    <generator>MediaWiki 1.35.0-wmf.36</generator>
    <case>first-letter</case>
    <namespaces>
      <namespace key="-2" case="first-letter">Media</namespace>
      <namespace key="-1" case="first-letter">Special</namespace>
      <namespace key="0" case="first-letter" />
      <namespace key="1" case="first-letter">Talk</namespace>
      <namespace key="2" case="first-letter">User</namespace>
      <namespace key="3" case="first-letter">User talk</namespace>
      <namespace key="4" case="first-letter">Wikipedia</namespace>
      <namespace key="5" case="first-letter">Wikipedia talk</namespace>
      <namespace key="6" case="first-letter">File</namespace>
      <namespace key="7" case="first-letter">File talk</namespace>
      <namespace key="8" case="first-letter">MediaWiki</namespace>
      <namespace key="9" case="first-letter">MediaWiki talk</namespace>
      <namespace key="10" case="first-letter">Template</namespace>
      <namespace key="11" case="first-letter">Template talk</namespace>
      <namespace key="12" case="first-letter">Help</namespace>
      <namespace key="13" case="first-letter">Help talk</namespace>
      <namespace key="14" case="first-letter">Category</namespace>
      <namespace key="15" case="first-letter">Category talk</namespace>
      <namespace key="100" case="first-letter">Portal</namespace>
      <namespace key="101" case="first-letter">Portal talk</namespace>
      <namespace key="108" case="first-letter">Book</namespace>
      <namespace key="109" case="first-letter">Book talk</namespace>
      <namespace key="118" case="first-letter">Draft</namespace>
      <namespace key="119" case="first-letter">Draft talk</namespace>
      <namespace key="446" case="first-letter">Education Program</namespace>
      <namespace key="447" case="first-letter">Education Program talk</namespace>
      <namespace key="710" case="first-letter">TimedText</namespace>
      <namespace key="711" case="first-letter">TimedText talk</namespace>
      <namespace key="828" case="first-letter">Module</namespace>
      <namespace key="829" case="first-letter">Module talk</namespace>
      <namespace key="2300" case="first-letter">Gadget</namespace>
      <namespace key="2301" case="first-letter">Gadget talk</namespace>
      <namespace key="2302" case="case-sensitive">Gadget definition</namespace>
      <namespace key="2303" case="case-sensitive">Gadget definition talk</namespace>
    </namespaces>
  </siteinfo>
  <page>
    <title>Bella Ferraro</title>
    <ns>0</ns>
    <id>37004613</id>
    <revision>
      <id>925025028</id>
      <parentid>916389909</parentid>
      <timestamp>2019-11-07T10:59:54Z</timestamp>
      <contributor>
        <ip>101.161.133.232</ip>
      </contributor>
      <comment>/* Performances on The X Factor */</comment>
      <model>wikitext</model>
      <format>text/x-wiki</format>
      <text bytes="19668" xml:space="preserve">{{EngvarB|date=August 2014}}
{{Use dmy dates|date=August 2014}}
{{Infobox musical artist
|name = Bella Ferraro 
|image = Bella_Ferraro_2012.jpg
|caption = Ferraro in 2012
|background = solo_singer
|birth_name = Isabella Ferraro 
|birth_date = {{Birth date and age|1994|08|20|df=y}}
|birth_place= Sydney, Australia
|origin = Sydney, Australia
|instrument = Vocals
|genre = [[Indie pop]], soul, [[soft rock]]&lt;!--Ferraro's genres are based on the songs she has sang.--&gt;
|occupation = Singer 
|yearsactive = 2012–present
|label = [[Sony Music Australia|Sony]]
|associated_acts =

}}
'''Bella Ferraro''' is an Australian singer most notable for finishing fourth on the [[The X Factor (Australia season 4)|fourth season]] of ''[[The X Factor (Australian TV series)|The X Factor Australia]]'' in 2012.

==Early life==
Ferraro was born and raised in Sydney.&lt;ref name="boyfactor"&gt;{{cite web|last=Knox|first=David|url=http://www.tvtonight.com.au/2012/09/boy-factor-on-the-x-factor.html|title=Boy factor on The X Factor|publisher=TV Tonight|date=13 September 2012|accessdate=13 September 2012}}&lt;/ref&gt; She began singing as a child. At age five, she became a member of the [[Australian Girls Choir]], who have performed at the annual [[Carols in the Domain]] and during [[Oprah Winfrey]]'s Australian tour. Ferraro left school in Year 12 to pursue a music career.&lt;ref name="xfactorbios"&gt;{{cite news|last=Byrnes|first=Holly|url=http://www.news.com.au/news/next-stop-the-live-shows-for-x-factors-top-12/story-fnejlvvj-1226473049998|title=X Factor – the live shows begin|work=[[The Daily Telegraph (Sydney)|The Daily Telegraph]]|publisher=News Limited|date=13 September 2012|accessdate=13 September 2012}}&lt;/ref&gt; She's of [[Italian Australians|Italian]] ancestry.

==Career==
===2012: ''The X Factor Australia''===
Ferraro successfully auditioned for the [[The X Factor (Australia season 4)|fourth season]] of ''[[The X Factor (Australian TV series)|The X Factor]]'' in 2012, singing [[Skinny Love#Birdy version|Skinny Love]], with a treatment based on the version by [[Birdy (musician)|Birdy]].&lt;ref name="bellabio"&gt;{{cite web |url=http://au.tv.yahoo.com/x-factor/contestants/bella-ferraro/ |title=The X-Factor Australia Contestant – Bella Ferraro |work=[[The X Factor (Australian TV series)|The X Factor Australia]] |publisher=[[Yahoo!7]] |date=13 September 2012 |archiveurl=https://www.webcitation.org/6AdLTme6L?url=http://au.tv.yahoo.com/x-factor/contestants/bella-ferraro/ |archivedate=12 September 2012 |url-status=dead |df=dmy }}&lt;/ref&gt; She was inspired to audition for the show after seeing the success of [[One Direction]] on the [[The X Factor (UK series 7)|UK version]].&lt;ref name="xfactorbios"/&gt;&lt;ref name="bellabio"/&gt; During the [[The X Factor (Australia season 4)#Super bootcamp|super bootcamp]] stage, Ferraro forgot the lyrics to the two songs she performed: [[Gotye]]'s "[[Somebody That I Used to Know]]" and [[Crowded House]]'s "[[Don't Dream It's Over]]".&lt;ref name="xfactorbios2"&gt;{{cite web|url=http://www.thehothits.com/news/34240/x-factor-australia%27s-top-twelve-revealed|title=X Factor Australia's Top Twelve Revealed|work=[[The Hot Hits Live from LA]]|publisher=MCM Entertainment|date=13 September 2012|accessdate=14 September 2012|archive-url=https://web.archive.org/web/20120921033203/http://www.thehothits.com/news/34240/x-factor-australia%27s-top-twelve-revealed|archive-date=21 September 2012|url-status=dead|df=dmy-all}}&lt;/ref&gt; For the first live performance show on 17 September 2012, Ferraro sang [[Matt Corby]]'s "Brother" and received a mixed response from the judges. [[Mel B]] said it was not the right song choice, while [[Ronan Keating]] disagreed saying that he loved the song choice and describing her performance as "beautiful".&lt;ref name="week1show"&gt;{{cite web|last=Lewdon|first=Courtney|url=http://www.throng.com.au/2012/09/the-x-factor-australia-season-four-top-12-performance-show-its-judges-choice/|title=The X Factor Australia – Season Four – Top 12 Performance Show: It's Judges Choice!|publisher=Throng. Throng Media|date=17 September 2012|accessdate=19 September 2012}}&lt;/ref&gt;

For the second live performance show, Ferraro performed a stripped back version of "[[What Makes You Beautiful]]". She received mixed reviews from the judges, who concluded that while the song was an appropriate choice, the arrangement did not match that week's theme, "Party Week".&lt;ref name="week2theme"&gt;{{cite web |url=http://au.tv.yahoo.com/x-factor/news/article/-/14954082/song-list-party-all-night/ |title=Song List: Party All Night! |work=The X Factor Australia |publisher=Yahoo!7 |archiveurl=https://www.webcitation.org/6Aw2UEEYz?url=http://au.tv.yahoo.com/x-factor/news/article/-/14954082/song-list-party-all-night/ |archivedate=25 September 2012 |url-status=dead |df=dmy }}&lt;/ref&gt; Her performance of "What Makes You Beautiful" debuted at number 62 on the [[ARIA Charts|ARIA Singles Chart]].&lt;ref name="ARIA Charts"/&gt; For the third live performance show, she sang "[[Big Yellow Taxi]]" by [[Joni Mitchell]] and received a positive response from the judges for her vocals, but mixed reviews over the choreography incorporated into the performance.&lt;ref name="week3theme"&gt;{{cite web |url=http://au.tv.yahoo.com/x-factor/news/article/-/15006513/song-list-top-10-hits/ |title=Song List: Top 10 Hits! |work=The X Factor Australia |publisher=Yahoo!7 |archiveurl=https://www.webcitation.org/6B5AJKVXf?url=http://au.tv.yahoo.com/x-factor/news/article/-/15006513/song-list-top-10-hits/ |archivedate=1 October 2012 |url-status=dead |df=dmy }}&lt;/ref&gt; Keating said the vocals were great but the dancing came in and it wasn't.&lt;ref name="week3theme"/&gt; Ferraro's performance of "Big Yellow Taxi" debuted at number 84.&lt;ref name="ARIA Charts"/&gt; For the fourth live show, she sang "[[Ray of Light (song)|Ray of Light]]" by [[Madonna (entertainer)|Madonna]] followed by the English version of "[[99 Red Balloons]]" from German band [[Nena (band)|Nena]] for the fifth live show. In week six of the live shows, Ferraro fell into the bottom two alongside Fourtunate but was saved after Mel B, [[Natalie Bassingthwaighte]], and [[Guy Sebastian]] all opted to eliminate Fourtunate.&lt;ref name="week6performers"&gt;{{cite web |last=Lewdon |first=Courtney |url=http://www.throng.com.au/2012/10/the-x-factor-australia-season-four-australia-picks-their-six/ |title=The X Factor Australia – Season Four – Australia Pics Their Six! |publisher=Throng. Throng Media |archiveurl=https://www.webcitation.org/6CsIzYGCC?url=http://www.throng.com.au/2012/10/the-x-factor-australia-season-four-australia-picks-their-six/ |archivedate=13 December 2012 |url-status=dead |df=dmy }}&lt;/ref&gt;

For the seventh live performance show, Ferraro sang [[The Temper Trap]]'s "[[Sweet Disposition]]".&lt;ref name="week7theme"&gt;{{cite web |url=http://au.tv.yahoo.com/x-factor/news/article/-/15243936/song-list-made-in-australia/ |title=Song List: Made in Australia! |work=The X Factor Australia |publisher=Yahoo!7 |archiveurl=https://www.webcitation.org/6Blf4K5wc?url=http://au.tv.yahoo.com/x-factor/news/article/-/15243936/song-list-made-in-australia/ |archivedate=29 October 2012 |url-status=dead |df=dmy }}&lt;/ref&gt;&lt;ref name="week7results"&gt;{{cite web |last=Lewdon |first=Courtney |url=http://www.throng.com.au/2012/10/the-x-factor-australia-season-four-the-top-six-dives-to-five/ |title=The X Factor Australia – Season Four – The Top Six Dives To Five |publisher=Throng. Throng Media |date=30 October 2012 |archiveurl=https://www.webcitation.org/6CsJ2v6f8?url=http://www.throng.com.au/2012/10/the-x-factor-australia-season-four-the-top-six-dives-to-five/ |archivedate=13 December 2012 |url-status=dead |df=dmy }}&lt;/ref&gt; Her performance of "Sweet Disposition" debuted at number 59.&lt;ref name="ARIA Charts"/&gt; For the eighth live performance show, Ferraro sang "[[Dreams (The Cranberries song)|Dreams]]" by [[The Cranberries]],&lt;ref name="week8theme"&gt;{{cite web |url=http://au.tv.yahoo.com/x-factor/news/article/-/15298653/song-list-judge-challenge/ |title=Song List: Judges' Challenge! |work=The X Factor Australia |publisher=Yahoo!7 |archiveurl=https://www.webcitation.org/6BxMNxSPl?url=http://au.tv.yahoo.com/x-factor/news/article/-/15298653/song-list-judge-challenge/ |archivedate=5 November 2012 |url-status=dead |df=dmy }}&lt;/ref&gt;&lt;ref name="week8results"&gt;{{cite web |last=Lewdon |first=Courtney |url=http://www.throng.com.au/2012/11/the-x-factor-australia-season-four-four-to-the-floor/ |title=The X Factor Australia – Season Four – Four to the Floor |publisher=Throng. Throng Media |date=6 November 2012 |archiveurl=https://www.webcitation.org/6CsJ5eoun?url=http://www.throng.com.au/2012/11/the-x-factor-australia-season-four-four-to-the-floor/ |archivedate=13 December 2012 |url-status=dead |df=dmy }}&lt;/ref&gt; and her performance debuted at number 82.&lt;ref name="ARIA Charts"/&gt; In the semi-finals of the live shows, Ferraro fell into the bottom two alongside [[The Collective (band)|The Collective]]; the result was a deadlock and so reverted to the earlier public vote. Ferraro was eliminated and thus placed fourth in the competition.&lt;ref name="week9theme"&gt;{{cite web |url=http://au.tv.yahoo.com/x-factor/news/article/-/15359856/song-list-power-passion/ |title=Song List: Power and Passion! |work=The X Factor Australia |publisher=Yahoo!7 |archiveurl=https://www.webcitation.org/6C6wxJgik?url=http://au.tv.yahoo.com/x-factor/news/article/-/15359856/song-list-power-passion/ |archivedate=12 November 2012 |url-status=dead |df=dmy }}&lt;/ref&gt;&lt;ref name="week9results"&gt;{{cite web |last=Lewdon |first=Courtney |url=http://www.throng.com.au/2012/11/the-x-factor-australia-season-four-semi-final-decider/ |title=The X Factor Australia – Season Four – Semi-final Decider |publisher=Throng. Throng Media |date=13 November 2012 |archiveurl=https://www.webcitation.org/6CsJB3a3g?url=http://www.throng.com.au/2012/11/the-x-factor-australia-season-four-semi-final-decider/ |archivedate=13 December 2012 |url-status=dead |df=dmy }}&lt;/ref&gt; Her performance of "[[The Last Day on Earth]]" debuted at number 90.&lt;ref name="ARIA Charts"/&gt;

====Performances on ''The X Factor''====
{{Color box|gold|border=darkgray}} denotes having reached the ARIA Singles Chart.&lt;br/&gt;{{Color box|lightblue|border=darkgray}} denotes having been in the bottom two.

{| class="wikitable collapsible collapsed" style="text-align:center;"
|-
|-
! scope="col" |Show
! scope="col" |Theme
! scope="col" |Song
! scope="col" |Original artist
! scope="col" |Order
! scope="col" |Result
|-
! scope="row"| Auditions
|rowspan="5"| Free choice
|"[[Skinny Love#Birdy version|Skinny Love]]"
|[[Birdy (musician)|Birdy]]
|rowspan="5"| N/A
|Through to super bootcamp  
|-
! scope="row"| Super bootcamp 1
|"[[The A Team (Ed Sheeran song)|The A Team]]"
|[[Ed Sheeran]]
| Through to stage 2 
|-
! scope="row"| Super bootcamp 2
|"[[Somebody That I Used to Know]]"
|[[Gotye]]
| Through to stage 3
|-
! scope="row"| Super bootcamp 3
| "[[Don't Dream It's Over]]"
|[[Crowded House]] 
| Through to home visits
|-
! scope="row"| Home visits
|"[[Heartbeats (song)|Heartbeats]]"
|[[Ellie Goulding]]
|Through to live shows
|- 
! scope="row"| Week 1
|Judges' Choice
|"Brother"
|[[Matt Corby]] 
|10
| Safe
|-style="background:gold;"
! scope="row"| Week 2
|Party All Night&lt;ref name="week2theme"/&gt;
|"[[What Makes You Beautiful]]"
|[[One Direction]]
|5
|Safe
|-style="background:gold;"
! scope="row"| Week 3
|Top 10 Hits&lt;ref name="week3theme"/&gt;
|"[[Big Yellow Taxi]]" 
|[[Joni Mitchell]]
|5
|Safe
|-
! scope="row"| Week 4
|Legends&lt;ref name="week4theme"&gt;{{cite web |url=http://au.tv.yahoo.com/x-factor/news/article/-/15062477/song-list-legends-week/ |title=Song List: Legends Week! |work=The X Factor Australia |publisher=Yahoo!7 |archiveurl=https://www.webcitation.org/6BFkz1ecZ?url=http://au.tv.yahoo.com/x-factor/news/article/-/15062477/song-list-legends-week/ |archivedate=8 October 2012 |url-status=dead |df=dmy }}&lt;/ref&gt;
|"[[Ray of Light (song)|Ray of Light]]" 
|[[Madonna (entertainer)|Madonna]]
|7
|Safe
|- 
! scope="row"| Week 5
|1980s
|"[[99 Luftballons|99 Red Balloons]]"
|[[Nena]]
|5
|Safe
|-style="background:lightblue;"
! scope="row" rowspan="2"| Week 6
|Latest and Greatest&lt;ref name="week6theme"&gt;{{cite web |url=http://au.tv.yahoo.com/x-factor/news/article/-/15180886/song-list-songs-of-now/ |title=Song List: Songs of Now! |work=The X Factor Australia |publisher=Yahoo!7 |archiveurl=https://www.webcitation.org/6Bb2EY5ln?url=http://au.tv.yahoo.com/x-factor/news/article/-/15180886/song-list-songs-of-now/ |archivedate=22 October 2012 |url-status=dead |df=dmy }}&lt;/ref&gt;
|"[[Shake It Out]]"
|[[Florence and the Machine|Florence + the Machine]]
|6
|Bottom two
|-
|Final showdown
|"Tonight"
|[[Lykke Li]]
|2
|Saved 
|- style="background:gold;"
! scope="row"| Week 7
|Made in Australia&lt;ref name="week7theme"/&gt;
|"[[Sweet Disposition]]"
|[[The Temper Trap]]
|5
|Safe
|- style="background:gold;"
! scope="row"| Week 8
|Judges' Challenge&lt;ref name="week8theme"/&gt;
|"[[Dreams (The Cranberries song)|Dreams]]"
|[[The Cranberries]]
|5
|Safe
|-style="background:lightblue;"
! scope="row" rowspan="4"| Semi-final
|rowspan="2"|Power and Passion&lt;ref name="week9theme"/&gt;
|"[[Bulletproof (La Roux song)|Bulletproof]]"
|[[La Roux]]
|3
|rowspan="2"|Bottom two
|-style="background:gold;"
|"[[The Last Day on Earth]]"
|[[Kate Miller-Heidke]]
|7
|-style="background:pink;"
|Final Showdown
|"[[Angel (Sarah McLachlan song)|Angel]]"
|[[Sarah McLachlan]]
|1
|Eliminated
|}

===2012–present: Record deal and singles===
After ''The X Factor'' ended, Ferraro obtained a recording contract with [[Sony Music Australia]] and released her debut single "[[Set Me on Fire]]" on 14 December 2012.&lt;ref&gt;{{cite web|url=https://itunes.apple.com/au/album/set-me-on-fire-single/id583727774|title=Set Me on Fire by Bella Ferraro|publisher=[[iTunes Store]] (Australia). [[Apple Inc.|Apple]]|accessdate=29 October 2013}}&lt;/ref&gt; The song peaked at number 36 on the ARIA Singles Chart on 30 December 2012.&lt;ref name="AUS"/&gt; Her second single "Forgot You", which features [[Will Singe]] of The Collective, was released on 18 October 2013 and peaked at number 75 on the ARIA Singles Chart.&lt;ref&gt;{{cite web|url=https://itunes.apple.com/au/album/forgot-you-feat.-will-singe/id724212803/|title=Forgot You (feat. Will Singe) by Bella Ferraro|publisher=iTunes Store (Australia). Apple|accessdate=29 October 2013}}&lt;/ref&gt;&lt;ref name="AUS"/&gt; Ferraro is no longer signed to Sony Music Australia,&lt;ref&gt;http://www.sonymusic.com.au/?path=artists&lt;/ref&gt; but continues to perform around Australia and has attracted fans from around the world.

==Artistry==
Ferraro cites [[Bon Iver]], [[Lykke Li]], [[Crystal Castles (band)|Crystal Castles]], [[Foals (band)|Foals]] and [[Two Door Cinema Club]] as her musical influences.&lt;ref name="bellabio"/&gt;

==Discography==

===Singles===
{| class="wikitable plainrowheaders" style="text-align:center;" border="1"
! scope="col" rowspan="2" style="width:14em;"| Title
! scope="col" rowspan="2" | Year
! scope="col" colspan="1"| Peak chart positions
&lt;!--! scope="col" rowspan="2" style="width:12em;"| [[Music recording sales certification|Certifications]]--&gt;
! scope="col" rowspan="2" style="width:10em;"| Album
|-
! scope="col" style="width:3em;font-size:90%;"| [[ARIA Charts|AUS]]&lt;br/&gt;&lt;ref name="AUS"&gt;Peak chart positions for singles on the ARIA Singles Chart:
*{{cite web|url=http://australian-charts.com/showinterpret.asp?interpret=Bella+Ferraro|title=Discography Bella Ferraro|publisher=Australian-charts.com. Hung Medien|accessdate=29 October 2013}}
*"Forgot You": {{cite web|last=Ryan|first=Gavin|url=http://www.noise11.com/news/aria-singles-it-is-still-about-katy-perry-20131026|title=ARIA Singles: It Is Still About Katy Perry|publisher=Noise11. Noise Network|date=26 October 2013|accessdate=26 October 2013}}&lt;/ref&gt;
|-
! scope="row"| "[[Set Me on Fire]]"
| 2012
| 36 
| rowspan="2" {{n/a}}
|-
! scope="row"| "Forgot You"&lt;br&gt;&lt;span style="font-size:85%;"&gt;(featuring [[Will Singe]])&lt;/span&gt;
| 2013
| 75
|-
&lt;!--| colspan="6" style="font-size:90%"| "—" denotes items which failed to chart in that country.--&gt;
|}

===Other charted songs===
{| class="wikitable plainrowheaders" style="text-align:center;" border="1"
! scope="col" rowspan="2" style="width:14em;"| Title
! scope="col" rowspan="2"| Year
! scope="col" colspan="1"| Peak chart positions
|-
! scope="col" style="width:3em;font-size:90%;"| [[ARIA Charts|AUS]]&lt;br/&gt;&lt;ref name="ARIA Charts"&gt;Peak chart positions for songs on the ARIA Singles Chart:
*"What Makes You Beautiful": {{cite web 
 |last=Ryan 
 |first=Gavin 
 |url=http://www.noise11.com/news/guy-sebastian-psy-fid-off-top-of-aria-chart-20120930 
 |title=Guy Sebastian PSY Fi'd Off Top of ARIA Chart 
 |publisher=Noise11. Noise Network 
 |date=30 September 2012 
 |archiveurl=https://www.webcitation.org/6B44eD1Se?url=http://www.noise11.com/news/guy-sebastian-psy-fid-off-top-of-aria-chart-20120930 
 |archivedate=30 September 2012 
 |url-status=dead 
 |df=dmy 
 }}
*"Big Yellow Taxi": {{cite web 
 |last=Ryan 
 |first=Gavin 
 |url=http://www.noise11.com/news/psy-gangham-style-stays-at-no-1-on-aria-chart-20121007 
 |title=PSY Gangham Style Stays at No. 1 on ARIA Chart 
 |publisher=Noise11. Noise Network 
 |date=7 October 2012 
 |archiveurl=https://www.webcitation.org/6BDs8eg7z?url=http://www.noise11.com/news/psy-gangham-style-stays-at-no-1-on-aria-chart-20121007 
 |archivedate=6 October 2012 
 |url-status=dead 
 |df=dmy 
 }}
*"Sweet Disposition": {{cite web 
 |last=Ryan 
 |first=Gavin 
 |url=http://www.noise11.com/news/psy-tops-aria-singles-for-6th-week-20121104 
 |title=Psy Tops ARIA Singles Chart For 6th Week 
 |publisher=Noise11. Noise Network 
 |date=4 November 2012 
 |archiveurl=https://www.webcitation.org/6BuQkAfAb?url=http://www.noise11.com/news/psy-tops-aria-singles-for-6th-week-20121104 
 |archivedate=3 November 2012 
 |url-status=dead 
 |df=dmy 
 }}
*"Dreams" : {{cite web 
 |last=Ryan 
 |first=Gavin 
 |url=http://www.noise11.com/news/swedish-house-mafia-replace-psy-on-aria-chart-20121111 
 |title=Swedish House Mafia Replace Psy on ARIA Chart 
 |publisher=Noise11. Noise Network 
 |date=11 November 2012 
 |archiveurl=https://www.webcitation.org/6C54Ebgi3?url=http://www.noise11.com/news/swedish-house-mafia-replace-psy-on-aria-chart-20121111 
 |archivedate=10 November 2012 
 |url-status=dead 
 |df=dmy 
 }}
*"The Last Day on Earth": {{cite web 
 |last=Ryan 
 |first=Gavin 
 |url=http://www.noise11.com/news/swedish-house-mafia-maintains-top-of-aria-chart-20121118 
 |title=Swedish House Mafia Maintains Top of ARIA Chart 
 |publisher=Noise11. Noise Network 
 |date=18 November 2012 
 |archiveurl=https://www.webcitation.org/6CFkFJRBb?url=http://www.noise11.com/news/swedish-house-mafia-maintains-top-of-aria-chart-20121118 
 |archivedate=17 November 2012 
 |url-status=dead 
 |df=dmy 
 }}&lt;/ref&gt;
|-
! scope="row"| "[[What Makes You Beautiful]]"
| rowspan="5"| 2012
| 62
|-
! scope="row"| "[[Big Yellow Taxi]]"
| 84
|-
! scope="row"| "[[Sweet Disposition]]"
| 59
|-
! scope="row"| "[[Dreams (The Cranberries song)|Dreams]]"
| 82
|-
! scope="row"| "[[The Last Day on Earth]]"
| 90
|-
|}

==References==
{{Reflist|2}}

==External links==
*{{Official website|https://web.archive.org/web/20131027021241/http://www.bellaferraromusic.com.au:80/}}

{{Commons category|Bella Ferraro}}

{{authority control}}

{{DEFAULTSORT:Ferraro, Bella}}
[[Category:Australian people of Italian descent]]
[[Category:Australian female singers]]
[[Category:The X Factor (Australian TV series) contestants]]
[[Category:Living people]]
[[Category:People from Sydney]]
[[Category:1994 births]]
[[Category:21st-century Australian singers]]
[[Category:21st-century women singers]]</text>
      <sha1>a15hg5t0pmgqvily51maiz1z5201fom</sha1>
    </revision>
  </page>
</mediawiki>
